repo-outline-tool/__init__.py
repo-outline-tool/repo_outline_tool.py
repo_outline_tool/__init__.py
repo_outline_tool/repo_outline_tool.py
repo_outline_tool-0.1.1.dist-info/METADATA
repo_outline_tool-0.1.1.dist-info/WHEEL
repo_outline_tool-0.1.1.dist-info/entry_points.txt
repo_outline_tool-0.1.1.dist-info/top_level.txt
repo_outline_tool-0.1.1.dist-info/RECORD
