Metadata-Version: 2.2
Name: repo-outline-tool
Version: 0.1.1
Summary: A tool to generate a markdown representation of a repository structure.
Home-page: https://github.com/tnatvu/repo-outline-tool
Author: Tina Vu
Author-email: tina.vtt@gmail.com
Classifier: Programming Language :: Python :: 3
Classifier: License :: OSI Approved :: MIT License
Classifier: Operating System :: OS Independent
Requires-Python: >=3.6
Dynamic: author
Dynamic: author-email
Dynamic: classifier
Dynamic: home-page
Dynamic: requires-python
Dynamic: summary
